{
  "Fort Sill": {
    "1": {
      "name": "Brad",
      "attribute": "High and Thight. Forever skinny",
      "rank": "Rank.E1",
      "location": "dfac"
    },
    "2": {
      "name": "Brad",
      "attribute": "Can dip a whole can of Skoal Wintergreen. Wears combat boots with his jeans",
      "rank": "Rank.E2",
      "location": "dfac"
    },
    "3": {
      "name": "Rogers",
      "attribute": "Has an associates in Political Science. Wears Nine Line Apparel. Says Hooah a lot",
      "rank": "Rank.E3",
      "location": "dfac"
    },
    "4": {
      "name": "Shad",
      "attribute": "Grumpy with gray hairs. Walks with a purpose.",
      "rank": "Rank.E6",
      "location": "px"
    },
    "5": {
      "name": "Arturo",
      "attribute": "Always having a cookout. Dances with products as he puts them into his cart.",
      "rank": "Rank.E6",
      "location": "market"
    },
    "6": {
      "name": "Mason",
      "attribute": "Hide n Seek Champion from his unit. Barracks Lawyer.",
      "rank": "Rank.E4",
      "location": "church"
    },
    "7": {
      "name": "John",
      "attribute": "Will pray with you and take you to choir practice.",
      "rank": "Rank.E6",
      "location": "church"
    },
    "8": {
      "name": "Brandon",
      "attribute": "Do you even lift, Bro.",
      "rank": "Rank.E5",
      "location": "gym"
    },
    "9": {
      "name": "Laginus",
      "attribute": "Got a DUI last week and avoids extra duty.",
      "rank": "Rank.E1",
      "location": "barracks"
    },
    "11": {
      "name": "Soko",
      "attribute": "Pot Belly. Always dirty because he's a mechanic. Never fixes anything tho.",
      "rank": "Rank.E2",
      "location": "barracks"
    },
    "12": {
      "name": "David",
      "attribute": "Just passed Ranger School. Lives off coffee and MRE's. Listens to Classic Rock.",
      "rank": "Rank.E3",
      "location": "barracks"
    },
    "13": {
      "name": "Stephen",
      "attribute": "Has a low-fade. Always preparing for SFAS. Won't tell you what it means.",
      "rank": "Rank.E4",
      "location": "barracks"
    }
  },
  "Fort Bliss": {
    "1": {
      "name": "Jose",
      "attribute": "Hasn't deployed because he has medical reason. Nobody knows what is wrong with him",
      "rank": "Rank.E9",
      "location": "starbucks"
    },
    "2": {
      "name": "Roger",
      "attribute": "Deployed for one month and was sent back for a injury sustained at the gym",
      "rank": "Rank.E6",
      "location": "starbucks"
    },
    "3": {
      "name": "Chip",
      "attribute": "Zero deployments and complains on how weak Warriors are now days",
      "rank": "Rank.E7",
      "location": "starbucks"
    },
    "4": {
      "name": "Dylan",
      "attribute": "Hides from all deployments and schools. Works strictly in Training Environments",
      "rank": "Rank.E8",
      "location": "theater"
    },
    "5": {
      "name": "Ryan",
      "attribute": "Motivator and places soldiers first.",
      "rank": "Rank.E9",
      "location": "theater"
    },
    "6": {
      "name": "Cody",
      "attribute": "Walks laps around the mall to lose weight but ends up taking a nap at Spencer's.",
      "rank": "Rank.E5",
      "location": "mall"
    },
    "7": {
      "name": "Justin",
      "attribute": "Low Fade and works behind a brown fence",
      "rank": "Rank.E7",
      "location": "mall"
    },
    "8": {
      "name": "Lambert",
      "attribute": "Believes that Warriors should be at work until 1900. Sends everybody to Airborne school.",
      "rank": "Rank.E8",
      "location": "mall"
    },
    "9": {
      "name": "Andy",
      "attribute": "Runs Marathons and you can always see him helping Warriors get in shape",
      "rank": "Rank.E9",
      "location": "mall"
    },
    "10": {
      "name": "Stephens",
      "attribute": "Is always having a pizza party in the Admin office. Hasn't filed paperwork in three years.",
      "rank": "Rank.E6",
      "location": "pizza"
    }

  }
}